crackdect/__init__.py
crackdect/crack_detection.py
crackdect/image_functions.py
crackdect/imagestack.py
crackdect/io.py
crackdect/stack_operations.py
crackdect/visualization.py
crackdect-0.2.dist-info/LICENSE
crackdect-0.2.dist-info/METADATA
crackdect-0.2.dist-info/WHEEL
crackdect-0.2.dist-info/top_level.txt
crackdect-0.2.dist-info/RECORD
