Metadata-Version: 2.1
Name: crackdect
Version: 0.2
Summary: crack detection for composite materials
Home-page: https://github.com/mattdrvo/CrackDect
Author: Matthias Drvoderic
Author-email: matthias.drvoderic@unileoben.ac.at
Keywords: crackdetection composites imageprocessing imagestack
Classifier: Development Status :: 4 - Beta
Classifier: Intended Audience :: Science/Research
Classifier: Topic :: Scientific/Engineering :: Image Processing
Classifier: Programming Language :: Python :: 3.8
Classifier: Operating System :: OS Independent
Classifier: License :: OSI Approved :: MIT License
Requires-Python: >=3.8
License-File: LICENSE
Requires-Dist: numpy
Requires-Dist: scipy
Requires-Dist: scikit-image
Requires-Dist: sqlalchemy
Requires-Dist: numba
Requires-Dist: matplotlib
Requires-Dist: psutil
